Metadata-Version: 2.1
Name: stskr-3
Version: 0.0
Summary: stskr_3
Author-email: ilapronin0700@gmail.com
